Metadata-Version: 2.1
Name: meu-investimento-mn
Version: 0.1
Summary: Uma biblioteca para cálculos de investimentos.
Home-page: https://github.com/m-novelli/projeto_fiap
Author: Marina N M
Author-email: mah.novelli@hotmail.com
Classifier: Programming Language :: Python :: 3
Classifier: License :: OSI Approved :: MIT License
Classifier: Operating System :: OS Independent
Requires-Python: >=3.6
License-File: LICENSE
